cs/app/osx/defaults.py
cs_app_osx_defaults-20250108.dist-info/WHEEL
cs_app_osx_defaults-20250108.dist-info/METADATA
cs_app_osx_defaults-20250108.dist-info/RECORD
