Metadata-Version: 2.3
Name: cs-app-osx-defaults
Version: 20250108
Summary: Access the MacOS defaults via the `defaults` command.
Keywords: python3
Author-email: Cameron Simpson <cs@cskk.id.au>
Classifier: Programming Language :: Python
Classifier: Programming Language :: Python :: 3
Classifier: Development Status :: 4 - Beta
Classifier: Intended Audience :: Developers
Classifier: Operating System :: OS Independent
Classifier: Topic :: Software Development :: Libraries :: Python Modules
Classifier: License :: OSI Approved :: GNU General Public License v3 or later (GPLv3+)
Requires-Dist: cs.app.osx.plist>=20221228
Requires-Dist: cs.cache>=20250103
Requires-Dist: cs.lex>=20250103
Requires-Dist: cs.psutils>=20250108.1
Requires-Dist: typeguard
Project-URL: MonoRepo Commits, https://bitbucket.org/cameron_simpson/css/commits/branch/main
Project-URL: Monorepo Git Mirror, https://github.com/cameron-simpson/css
Project-URL: Monorepo Hg/Mercurial Mirror, https://hg.sr.ht/~cameron-simpson/css
Project-URL: Source, https://github.com/cameron-simpson/css/blob/main/lib/python/cs/app/osx/defaults.py
